Workbook

Sheet merged
A1: Company | B1: Tesla | F1: BYD | J1: Tesla | N1: BYD | R1: Tesla | V1: BYD
A2: Period | B2: 2023Q1 | C2: 2023Q2 | D2: 2023Q3 | E2: 2023Q4 | F2: 2023Q1 | G2: 2023Q2 | H2: 2023Q3 | I2: 2023Q4 | J2: 2024Q1 | K2: 2024Q2 | L2: 2024Q3 | M2: 2024Q4 | N2: 2024Q1 | O2: 2024Q2 | P2: 2024Q3 | Q2: 2024Q4 | R2: 2025Q1 | S2: 2025Q2 | T2: 2025Q3 | U2: 2025Q4 | V2: 2025Q1 | W2: 2025Q2 | X2: 2025Q3 | Y2: 2025Q4
A3: AI Integration
A4: # of AI features per product added | B4: 3 | C4: 0 | D4: 0 | E4: 0 | F4: 7 | G4: 0 | H4: 0 | I4: 0 | J4: 0 | K4: 0 | L4: 0 | M4: 1 | N4: 1 | O4: 0 | P4: 0 | Q4: 0 | R4: 2 | S4: 0 | T4: 0 | U4: 0 | V4: 1 | W4: 0 | X4: 0 | Y4: 0
A5: Passive AI (navigation, recommendations) | B5: 2 | C5: 0 | D5: 0 | E5: 0 | F5: 3 | G5: 0 | H5: 0 | I5: 0 | J5: 0 | K5: 0 | L5: 0 | M5: 0 | N5: 0 | O5: 0 | P5: 0 | Q5: 0 | R5: 1 | S5: 0 | T5: 0 | U5: 0 | V5: 0 | W5: 0 | X5: 0 | Y5: 0
A6: Interactive AI (voice assistant, chatbot) | B6: 0 | C6: 0 | D6: 0 | E6: 0 | F6: 1 | G6: 0 | H6: 0 | I6: 0 | J6: 0 | K6: 0 | L6: 0 | M6: 0 | N6: 0 | O6: 0 | P6: 0 | Q6: 0 | R6: 0 | S6: 0 | T6: 0 | U6: 0 | V6: 0 | W6: 0 | X6: 0 | Y6: 0
A7: Adaptive AI (personalization, learning behavior) | B7: 1 | C7: 0 | D7: 0 | E7: 0 | F7: 3 | G7: 0 | H7: 0 | I7: 0 | J7: 0 | K7: 0 | L7: 0 | M7: 1 | N7: 1 | O7: 0 | P7: 0 | Q7: 0 | R7: 1 | S7: 0 | T7: 0 | U7: 0 | V7: 1 | W7: 0 | X7: 0 | Y7: 0
A8: AI-related OTA and software-change intensity | B8: 0 | C8: 0 | D8: 0 | E8: 0 | F8: 3 | G8: 3 | H8: 3 | I8: 3 | J8: 2 | K8: 2 | L8: 2 | M8: 2 | N8: 5 | O8: 5 | P8: 5 | Q8: 5 | R8: 3 | S8: 3 | T8: 3 | U8: 3 | V8: 4 | W8: 4 | X8: 4 | Y8: 4
A9: App ecosystem depth (0-3) | B9: 3 | C9: 3 | D9: 3 | E9: 3 | F9: 1 | G9: 1 | H9: 2 | I9: 2 | J9: 3 | K9: 3 | L9: 3 | M9: 3 | N9: 2 | O9: 2 | P9: 2 | Q9: 2 | R9: 3 | S9: 3 | T9: 3 | U9: 3 | V9: 2 | W9: 2 | X9: 2 | Y9: 2
A10: Localization Depth
A11: Product/service adaptation ( 0 imports only / 1 local assembly / 2 partial production / 3 full local manufacturing) | B11: 2 | C11: 2 | D11: 2 | E11: 2 | F11: 0 | G11: 0 | H11: 0 | I11: 0 | J11: 2 | K11: 2 | L11: 2 | M11: 2 | N11: 0 | O11: 0 | P11: 0 | Q11: 0 | R11: 3 | S11: 3 | T11: 3 | U11: 3 | V11: 0 | W11: 0 | X11: 0 | Y11: 0
A12: Local language UX/UI ( 0 none / 1 translation only / 2 adapted interface / 3 culturally adapted UX) | B12: 1 | C12: 1 | D12: 1 | E12: 1 | F12: 1 | G12: 1 | H12: 1 | I12: 1 | J12: 1 | K12: 1 | L12: 1 | M12: 1 | N12: 2 | O12: 2 | P12: 2 | Q12: 2 | R12: 2 | S12: 2 | T12: 3 | U12: 3 | V12: 2 | W12: 2 | X12: 2 | Y12: 2
A13: Infrastructure
A14: Local production facilities (binary) | B14: 1 | C14: 1 | D14: 1 | E14: 1 | F14: 0 | G14: 0 | H14: 0 | I14: 0 | J14: 1 | K14: 1 | L14: 1 | M14: 1 | N14: 0 | O14: 0 | P14: 0 | Q14: 0 | R14: 1 | S14: 1 | T14: 1 | U14: 1 | V14: 0 | W14: 0 | X14: 0 | Y14: 0
A15: Local data center (binary) | B15: 1 | C15: 1 | D15: 1 | E15: 1 | F15: 0 | G15: 0 | H15: 0 | I15: 0 | J15: 1 | K15: 1 | L15: 1 | M15: 1 | N15: 0 | O15: 0 | P15: 0 | Q15: 0 | R15: 1 | S15: 1 | T15: 1 | U15: 1 | V15: 0 | W15: 0 | X15: 1 | Y15: 1
A16: Local R&D or design hubs (binary) | B16: 1 | C16: 1 | D16: 1 | E16: 1 | F16: 0 | G16: 0 | H16: 0 | I16: 0 | J16: 1 | K16: 1 | L16: 1 | M16: 1 | N16: 0 | O16: 0 | P16: 0 | Q16: 0 | R16: 1 | S16: 1 | T16: 1 | U16: 1 | V16: 0 | W16: 0 | X16: 0 | Y16: 0
A17: Regulatory Fit
A18: Compliance statements in CSR/ESG reports | B18: 1 = general compliance language | F18: 1 (basic system) | J18: 1 = general compliance language | N18: 2 (formalized + code + privacy system) | R18: 1 = general compliance language | V18: 3 (operational + region-specific)
A19: OTA and data localization compliance | B19: 2 = strong localization + OTA compliance evidence | F19: 0 | J19: 2 = strong localization + OTA compliance evidence | N19: 1 (framework) | R19: 2 = strong localization + OTA compliance evidence | V19: 3 (fully operational + EU data + OTA governance)
A20: Regulatory approvals | B20: 1 = operating approval, but no confirmed full FSD approval | F20: 1 (implicit compliance) | J20: 2 = data-security compliance recognized; restrictions eased; still no confirmed full FSD approval | N20: 2 (continued compliance) | R20: 2 = data-security compliance recognized; restrictions eased; still no confirmed full FSD approval | V20: 3 (continuous WVTA compliance)
A21: Compliance certifications | B21: 1 = vehicle market access implied, but no directly verified annual certification record yet | F21: 1 = basic group-level compliance, risk management, internal control, and regulatory compliance language. | J21: 2 = external compliance validation for data handling, but not yet a full autonomous-driving approval | N21: 3 (ISO 21434 + UN R155/R156) | R21: 2 = external compliance validation for data handling, but not yet a full autonomous-driving approval | V21: 3 (ISO 21434 + UN R155/R156)
A22: engagement with AI-enabled digital services
A23: Ratings Volume | L23: =UE!C2 -> 368 | M23: =UE!C3 -> 975 | O23: =UE!C4 -> 126 | P23: =UE!C5 -> 302 | Q23: =UE!C6 -> 300 | R23: 479 | S23: =UE!C8 -> 321 | T23: =UE!C9 -> 845 | U23: =UE!C10 -> 4536 | V23: =UE!C11 -> 295 | W23: =UE!C12 -> 494 | X23: =UE!C13 -> 354 | Y23: =UE!C14 -> 499
A24: Positive Share | L24: =UE!E2 -> 0.79619565 | M24: =UE!E3 -> 0.86564103 | O24: =UE!E4 -> 0.85714286 | P24: =UE!E5 -> 0.4602649 | Q24: =UE!E6 -> 0.53666667 | R24: =UE!E7 -> 0.79749478 | S24: =UE!E8 -> 0.71962617 | T24: =UE!E9 -> 0.89704142 | U24: =UE!E10 -> 0.96296296 | V24: =UE!E11 -> 0.56271186 | W24: =UE!E12 -> 0.64777328 | X24: =UE!E13 -> 0.57909605 | Y24: =UE!E14 -> 0.58517034
A25: Average Rating | L25: =UE!F2 -> 4.2934783 | M25: =UE!F3 -> 4.4748718 | O25: =UE!F4 -> 4.4444444 | P25: =UE!F5 -> 3.2847682 | Q25: =UE!F6 -> 3.2533333 | R25: =UE!F7 -> 4.2693111 | S25: =UE!F8 -> 3.9719626 | T25: =UE!F9 -> 4.5964497 | U25: =UE!F10 -> 4.8567019 | V25: =UE!F11 -> 3.2101695 | W25: =UE!F12 -> 3.5060729 | X25: =UE!F13 -> 3.1892655 | Y25: =UE!F14 -> 4.0781563
A26: Rating Velocity | L26: =UE!D2 -> 0.051794511 | M26: =UE!D3 -> 0.13046969 | O26: =UE!D4 -> 0.17524339 | P26: =UE!D5 -> 0.35739645 | Q26: =UE!D6 -> 0.26155187 | R26: =UE!D7 -> 0.056699811 | S26: =UE!D8 -> 0.035958329 | T26: =UE!D9 -> 0.091371107 | U26: =UE!D10 -> 0.44942039 | V26: =UE!D11 -> 0.20387008 | W26: =UE!D12 -> 0.28358209 | X26: =UE!D13 -> 0.15831843 | Y26: =UE!D14 -> 0.19266409
A27: Host market capacity (control variable)
A28: GDP Nominal in trillion USD | B28: 4.12 | C28: 4.45 | D28: 4.63 | E28: 5.03 | F28: 1.14 | G28: 1.12 | H28: 1.15 | I28: 1.19 | J28: 4.23 | K28: 4.56 | L28: 4.74 | M28: 5.19 | N28: 1.17 | O28: 1.16 | P28: 1.18 | Q28: 1.21 | R28: 4.42 | S28: 4.74 | T28: 4.92 | U28: 5.39 | V28: 1.2 | W28: 1.19 | X28: 1.22 | Y28: 1.26
A29: Passenger cars sales in units | B29: 4272713 | C29: 5259363 | D29: 5709270 | E29: 6475311 | F29: 666818 | G29: 730052 | H29: 741196 | I29: 706543 | J29: 4827894 | K29: 5010832 | L29: 5735838 | M29: 7319077 | N29: 694785 | O29: 776856 | P29: 644433 | Q29: 701257 | R29: 5114971 | S29: 5778072 | T29: 6105759 | U29: 6736902 | V29: 664571 | W29: 738218 | X29: 707559 | Y29: 747243
A31: Sources: | B31: China | F31: Germany
A32: GDP | B32: https://www.stats.gov.cn/english/ | F32: https://www.destatis.de/EN/Themes/Economy/National-Accounts-Domestic-Product/Tables/domestic-product-q-gdp.html
B33: or file on GDP China | F33: or file on GDP Germany
A35: Passenger car sales: | B35: Tesla Market success data-sales folder | F35: Market Success folder (BYD)
B36: page title: 总体市场-狭义乘用车产销情况（YYYY年M月份) = Narrow passenger-car production and sales situation (date) | F36: alternative_Antriebe reports
B37: row 狭义乘用车 (narrow passenger vehicles) | F37: quarterly total German passenger-car market sales (Pkw Insgesamt)
B38: column 零售 (retail) | F38: cumulative total passenger-car market sales in the quarter-end report used to substract and get quarterly numbers
B39: in blue circle in 2023-1 in sales, in purple or blue highlight for others

Sheet UE
A1: Firm | B1: Quarter | C1: Ratings volume | D1: Rating velocity | E1: Positive share | F1: Average rating
A2: Tesla | B2: 2024Q3 | C2: 368 | D2: =368 / 7105 -> 0.051794511 | E2: =(31 + 262) / C2 -> 0.79619565 | F2: =1580 / C2 -> 4.2934783
A3: Tesla | B3: 2024Q4 | C3: 975 | D3: =975 / 7473 -> 0.13046969 | E3: =(69 + 775) / C3 -> 0.86564103 | F3: =4363 / C3 -> 4.4748718
A4: BYD | B4: 2024Q2 | C4: 126 | D4: =126 / 719 -> 0.17524339 | E4: =(5 + 103) / C4 -> 0.85714286 | F4: =560 / C4 -> 4.4444444
A5: BYD | B5: 2024Q3 | C5: 302 | D5: =302 / 845 -> 0.35739645 | E5: =(-16 + 155) / C5 -> 0.4602649 | F5: =992 / C5 -> 3.2847682
A6: BYD | B6: 2024Q4 | C6: 300 | D6: =300 / 1147 -> 0.26155187 | E6: =(105 + 56) / C6 -> 0.53666667 | F6: =976 / C6 -> 3.2533333
A7: Tesla | B7: 2025Q1 | C7: =merged!R23 -> 479 | D7: =479 / 8448 -> 0.056699811 | E7: =(37 + 345) / C7 -> 0.79749478 | F7: =2045 / C7 -> 4.2693111
A8: Tesla | B8: 2025Q2 | C8: 321 | D8: =321 / 8927 -> 0.035958329 | E8: =(26 + 205) /C8 -> 0.71962617 | F8: =1275 /C8 -> 3.9719626
A9: Tesla | B9: 2025Q3 | C9: 845 | D9: =845 / 9248 -> 0.091371107 | E9: =(43 + 715) / C9 -> 0.89704142 | F9: =3884 / C9 -> 4.5964497
A10: Tesla | B10: 2025Q4 | C10: 4536 | D10: =4536 / 10093 -> 0.44942039 | E10: =(107 + 4261) / C10 -> 0.96296296 | F10: =22030 / C10 -> 4.8567019
A11: BYD | B11: 2025Q1 | C11: 295 | D11: =295 / 1447 -> 0.20387008 | E11: =(87 + 79) / C11 -> 0.56271186 | F11: =947 / C11 -> 3.2101695
A12: BYD | B12: 2025Q2 | C12: 494 | D12: =494 / 1742 -> 0.28358209 | E12: =(58 + 262) / C12 -> 0.64777328 | F12: =1732 / C12 -> 3.5060729
A13: BYD | B13: 2025Q3 | C13: 354 | D13: =354 / 2236 -> 0.15831843 | E13: =(121 + 84) / C13 -> 0.57909605 | F13: =1129 / C13 -> 3.1892655
A14: BYD | B14: 2025Q4 | C14: 499 | D14: =499 / 2590 -> 0.19266409 | E14: =(-2 + 294) / C14 -> 0.58517034 | F14: =2035 / C14 -> 4.0781563
A18: Source: User Engagement data folders
A19: CSV files for play store or app store

Sheet MS
A1: Tesla
A2: Quarter | B2: Tesla sales | C2: NEV retail total | D2: EV market share | E2: Rank | F2: Brand ranking score | H2: Sources
A3: 2023Q1 | B3: 137,000 | C3: 1,314,000 | D3: 0.104 | E3: 2 | F3: 1-(2-1)/(15-1)=0.928571 | H3: NEV retail total: Market Success Data folder, nev folder | J3: If rank was not clear, it was calculated this way:
A4: 2023Q2 | B4: 157,000 | C4: 1,772,000 | D4: 0.089 | E4: 2 | F4: 1-(2-1)/(10-1)=0.888889 | H4: p.6 of each report
A5: 2023Q3 | B5: 140,000 | C5: 2,103,000 | D5: 0.067 | E5: 2 | F5: 1-(2-1)/(10-1)=0.888889 | H5: column: NEV 合计 | J5: BYD: 3,484,525 - 2,542,239 = 942,286
A6: 2023Q4 | B6: 170,000 | C6: 2,553,000 | D6: 0.067 | E6: 2 | F6: 1-(2-1)/(10-1)=0.888889 | H6: line: 2(*month number*)月份 | J6: Geely: 1,564,562 - 1,092,148 = 472,414
A7: 2024Q1 | B7: 132.398 | C7: 1,765,000 | D7: 0.075 | E7: 3 | F7: 1-(3-1)/(10-1)=0.777778 | H7: number*10,000 | J7: SAIC-GM-Wuling: 772,147 - 507,424 = 264,723
A8: 2024Q2 | B8: 145,000 | C8: 2,334,000 | D8: 0.062 | E8: 3 | F8: 1-(3-1)/(10-1)=0.777778 | H8: Tesla sales: Market Success Data folder, sales folder | J8: Harmony / 鸿蒙智行: 588,549 - 348,858 = 239,691
A9: 2024Q3 | B9: 182.442 | C9: 3,026,000 | D9: 0.060 | E9: 3 | F9: 1-(3-1)/(10-1)=0.777778 | H9: table: 2025年12月 新能源市场狭义乘用车TOP10厂商零售销量 | J9: Changan: 789,141 - 579,755 = 209,386
A10: 2024Q4 | B10: 196.902 | C10: 3,768,000 | D10: 0.052 | E10: 4 | F10: 1-(4-1)/(10-1)=0.666667 | H10: company name: 特斯拉中国 (Tesila Zhongguo or Tesla China) | J10: Tesla: 625,698 - 432,704 = 192,994
A11: 2025Q1 | B11: 134.607 | C11: 2,418,000 | D11: 0.056 | E11: 5 | F11: 1-(5-1)/(10-1)=0.555556 | H11: column 序 = rank
A12: 2025Q2 | B12: 128.803 | C12: 3,044,000 | D12: 0.042 | E12: 5 | F12: 1-(5-1)/(10-1)=0.555556 | J12: So 5 brands are above Tesla, which means:
A13: 2025Q3 | B13: 169.294 | C13: 3,400,000 | D13: 0.050 | E13: 5 | F13: 1-(5-1)/(10-1)=0.555556 | J13: Tesla 2025 Q4 rank = 6
A14: 2025Q4 | B14: 192.994 | C14: 3,939,000 | D14: 0.049 | E14: 6 | F14: 1-(6-1)/(10-1)=0.444444
B16: *Sales are calculated as monthly sums or as differences between cumulatives (subject to rounding up in monthly variables)
A21: 2023
A22: Report | B22: Period | C22: BYD BEV registrations | D22: monthly | E22: quarterly | F22: BEV overall sales | G22: monthly | H22: quarterly | I22: market share | J22: ranking | K22: overall brands number | L22: relative position | O22: Reports are in the Market Success Data folder
A23: Jan report | B23: Jan 2023 | C23: 50 | D23: 50 | F23: 18136 | G23: 18136
A24: Feb report | B24: Jan–Feb 2023 | C24: 57 | D24: =C24-C23 -> 7 | F24: 50611 | G24: =F24-F23 -> 32475
A25: Mar report | B25: Jan–Mar 2023 | C25: 64 | D25: =C25-C24 -> 7 | E25: =D23+D24+D25 -> 64 | F25: 94736 | G25: =F25-F24 -> 44125 | H25: =G23+G24+G25 -> 94736 | I25: =E25/H25 -> 0.00067556156 | J25: 28 | K25: 35 | L25: =1-(J25-1)/(K25-1) -> 0.20588235
A26: Apr report | B26: Jan–Apr 2023 | C26: 107 | D26: =C26-C25 -> 43 | F26: 124476 | G26: =F26-F25 -> 29740
A27: May report | B27: Jan–May 2023 | C27: 161 | D27: =C27-C26 -> 54 | F27: 167256 | G27: =F27-F26 -> 42780
A28: Jun report | B28: Jan–Jun 2023 | C28: 224 | D28: =C28-C27 -> 63 | E28: =D26+D27+D28 -> 160 | F28: 220244 | G28: =F28-F27 -> 52988 | H28: =G26+G27+G28 -> 125508 | I28: =E28/H28 -> 0.0012748191 | J28: 26 | K28: 37 | L28: =1-(J28-1)/(K28-1) -> 0.30555556
A29: Jul report | B29: Jan–Jul 2023 | C29: 628 | D29: =C29-C28 -> 404 | F29: 268926 | G29: =F29-F28 -> 48682
A30: Aug report | B30: Jan–Aug 2023 | C30: 2662 | D30: =C30-C29 -> 2034 | F30: 355575 | G30: =F30-F29 -> 86649
A31: Sep report | B31: Jan–Sep 2023 | C31: 2858 | D31: =C31-C30 -> 196 | E31: =D29+D30+D31 -> 2634 | F31: 387289 | G31: =F31-F30 -> 31714 | H31: =G29+G30+G31 -> 167045 | I31: =E31/H31 -> 0.015768206 | J31: 18 | K31: 41 | L31: =1-(J31-1)/(K31-1) -> 0.575
A32: Oct report | B32: Jan–Oct 2023 | C32: 3084 | D32: =C32-C31 -> 226 | F32: 424623 | G32: =F32-F31 -> 37334
A33: Nov report | B33: Jan–Nov 2023 | C33: 3434 | D33: =C33-C32 -> 350 | F33: 469565 | G33: =F33-F32 -> 44942
A34: Dec report | B34: Jan–Dec 2023 | C34: 4135 | D34: =C34-C33 -> 701 | E34: =D32+D33+D34 -> 1277 | F34: 524219 | G34: =F34-F33 -> 54654 | H34: =G32+G33+G34 -> 136930 | I34: =E34/H34 -> 0.009325933 | J34: 16 | K34: 44 | L34: =1-(J34-1)/(K34-1) -> 0.65116279
A36: 2024
A37: Report | B37: Period | C37: BYD BEV registrations | D37: monthly | E37: quarterly | F37: BEV overall sales | G37: monthly | H37: quarterly | I37: market share | J37: ranking | K37: overall brands number | L37: relative position
A38: Jan report | B38: Jan 2024 | C38: 139 | D38: 139 | F38: 22474 | G38: 22474 | L38: relative_position = 1 − (rank − 1)/(brands − 1)
A39: Feb report | B39: Jan–Feb 2024 | C39: 233 | D39: =C39-C38 -> 94 | F39: 49953 | G39: =F39-F38 -> 27479
A40: Mar report | B40: Jan–Mar 2024 | C40: 393 | D40: =C40-C39 -> 160 | E40: =D38+D39+D40 -> 393 | F40: 81337 | G40: =F40-F39 -> 31384 | H40: =G38+G39+G40 -> 81337 | I40: =E40/H40 -> 0.0048317494 | J40: 27 | K40: 38 | L40: =1-(J40-1)/(K40-1) -> 0.2972973
A41: Apr report | B41: Jan–Apr 2024 | C41: 576 | D41: =C41-C40 -> 183 | F41: 111005 | G41: =F41-F40 -> 29668
A42: May report | B42: Jan–May 2024 | C42: 776 | D42: =C42-C41 -> 200 | F42: 140713 | G42: =F42-F41 -> 29708
A43: Jun report | B43: Jan–Jun 2024 | C43: 1165 | D43: =C43-C42 -> 389 | E43: =D41+D42+D43 -> 772 | F43: 184125 | G43: =F43-F42 -> 43412 | H43: =G41+G42+G43 -> 102788 | I43: =E43/H43 -> 0.0075106044 | J43: 24 | K43: 41 | L43: =1-(J43-1)/(K43-1) -> 0.425
A44: Jul report | B44: Jan–Jul 2024 | C44: 1386 | D44: =C44-C43 -> 221 | F44: 214887 | G44: =F44-F43 -> 30762
A45: Aug report | B45: Jan–Aug 2024 | C45: 1586 | D45: =C45-C44 -> 200 | F45: 241911 | G45: =F45-F44 -> 27024
A46: Sep report | B46: Jan–Sep 2024 | C46: 1723 | D46: =C46-C45 -> 137 | E46: =D44+D45+D46 -> 558 | F46: 276390 | G46: =F46-F45 -> 34479 | H46: =G44+G45+G46 -> 92265 | I46: =E46/H46 -> 0.0060477971 | J46: 21 | K46: 42 | L46: =1-(J46-1)/(K46-1) -> 0.51219512
A47: Oct report | B47: Jan–Oct 2024 | C47: 2066 | D47: =C47-C46 -> 343 | F47: 311881 | G47: =F47-F46 -> 35491
A48: Nov report | B48: Jan–Nov 2024 | C48: 2472 | D48: =C48-C47 -> 406 | F48: 347048 | G48: =F48-F47 -> 35167
A49: Dec report | B49: Jan–Dec 2024 | C49: 2781 | D49: =C49-C48 -> 309 | E49: =D47+D48+D49 -> 1058 | F49: 380609 | G49: =F49-F48 -> 33561 | H49: =G47+G48+G49 -> 104219 | I49: =E49/H49 -> 0.0101517 | J49: 19 | K49: 44 | L49: =1-(J49-1)/(K49-1) -> 0.58139535
A51: 2025
A52: Report | B52: Period | C52: BYD BEV registrations | D52: monthly | E52: quarterly | F52: BEV overall sales | G52: monthly | H52: quarterly | I52: market share | J52: ranking | K52: overall brands number | L52: relative position
A53: Jan report | B53: Jan 2025 | C53: 204 | D53: 204 | F53: 34498 | G53: 34498
A54: Feb report | B54: Jan–Feb 2025 | C54: 364 | D54: =C54-C53 -> 160 | F54: 70447 | G54: =F54-F53 -> 35949
A55: Mar report | B55: Jan–Mar 2025 | C55: 979 | D55: =C55-C54 -> 615 | E55: =D53+D54+D55 -> 979 | F55: 112968 | G55: =F55-F54 -> 42521 | H55: =G53+G54+G55 -> 112968 | I55: =E55/H55 -> 0.008666171 | J55: 16 | K55: 40 | L55: =1-(J55-1)/(K55-1) -> 0.61538462
A56: Apr report | B56: Jan–Apr 2025 | C56: 2028 | D56: =C56-C55 -> 1049 | F56: 158503 | G56: =F56-F55 -> 45535
A57: May report | B57: Jan–May 2025 | C57: 3251 | D57: =C57-C56 -> 1223 | F57: 201563 | G57: =F57-F56 -> 43060
A58: Jun report | B58: Jan–Jun 2025 | C58: 4544 | D58: =C58-C57 -> 1293 | E58: =D56+D57+D58 -> 3565 | F58: 248726 | G58: =F58-F57 -> 47163 | H58: =G56+G57+G58 -> 135758 | I58: =E58/H58 -> 0.026259963 | J58: 14 | K58: 43 | L58: =1-(J58-1)/(K58-1) -> 0.69047619
A59: Jul report | B59: Jan–Jul 2025 | C59: 5125 | D59: =C59-C58 -> 581 | F59: 297340 | G59: =F59-F58 -> 48614
A60: Aug report | B60: Jan–Aug 2025 | C60: 5809 | D60: =C60-C59 -> 684 | F60: 336707 | G60: =F60-F59 -> 39367
A61: Sep report | B61: Jan–Sep 2025 | C61: 7146 | D61: =C61-C60 -> 1337 | E61: =D59+D60+D61 -> 2602 | F61: 382202 | G61: =F61-F60 -> 45495 | H61: =G59+G60+G61 -> 133476 | I61: =E61/H61 -> 0.019494141 | J61: 12 | K61: 45 | L61: =1-(J61-1)/(K61-1) -> 0.75
A62: Oct report | B62: Jan–Oct 2025 | C62: 7770 | D62: =C62-C61 -> 624 | F62: 434627 | G62: =F62-F61 -> 52425
A63: Nov report | B63: Jan–Nov 2025 | C63: 8949 | D63: =C63-C62 -> 1179 | F63: 490368 | G63: =F63-F62 -> 55741
A64: Dec report | B64: Jan–Dec 2025 | C64: 11167 | D64: =C64-C63 -> 2218 | E64: =D62+D63+D64 -> 4021 | F64: 545142 | G64: =F64-F63 -> 54774 | H64: =G62+G63+G64 -> 162940 | I64: =E64/H64 -> 0.024677796 | J64: 10 | K64: 47 | L64: =1-(J64-1)/(K64-1) -> 0.80434783

Sheet ai types
A1: Company | B1: Quarter | C1: Observed AI features | D1: Passive AI | E1: Interactive AI | F1: Adaptive AI
A2: Tesla | B2: 2023Q1 | C2: Autopilot/ADAS, OTA updates, Sentry Mode | D2: 2 | E2: 0 | F2: 1
A3: Tesla | B3: 2024Q4 | C3: Actually Smart Summon in China | D3: 0 | E3: 0 | F3: 1
A4: Tesla | B4: 2025Q1 | C4: FSD-like assisted-driving update; local mapping/navigation support | D4: 1 | E4: 0 | F4: 1
A5: BYD | B5: 2023Q1 | C5: ADAS, intelligent voice control, connected/cloud services, OTA updates | D5: 3 | E5: 1 | F5: 3
A6: BYD | B6: 2024Q1 | C6: XUANJI intelligent vehicle architecture | D6: 0 | E6: 0 | F6: 1
A7: BYD | B7: 2025Q1 | C7: God’s Eye / DiPilot intelligent-driving expansion | D7: 0 | E7: 0 | F7: 1

Sheet ota updates
A1: Company | B1: Year | C1: OTA/software-change intensity used in dataset | D1: Main observed update evidence | E1: Descriptive classification | F1: Source
A2: Tesla | B2: 2023 | C2: 0 | D2: China recall update related to regenerative braking strategy and accelerator-warning behavior was identified, but excluded because it was treated as a safety/software fix rather than AI-related digital functionality. | E2: Not included in AI-related OTA count | F2: Reuters, 2023
A3: Tesla | B3: 2024 | C3: 2 | D3: Actually Smart Summon rollout in China; smart-driving capability expansion around China-specific vehicle/software ecosystem. | E3: New AI functionality; feature improvement / smart-driving capability support | F3: CnEVPost, 2024a; CnEVPost, 2024b
A4: Tesla | B4: 2025 | C4: 3 | D4: FSD-like city-road assisted-driving software update in China, including navigation-route driving, intersection and traffic-signal behavior, and driver-attention monitoring. | E4: New AI functionality; feature improvement; localization support | F4: CnEVPost, 2025
A5: BYD | B5: 2023 | C5: 3 | D5: Early European/German software localization and connected-service rollout, including German-language menus/navigation and CarPlay/Android Auto-related functionality. | E5: Localization update; feature improvement; connected-service improvement | F5: GoingElectric, 2023; WhichCar, 2023
A6: BYD | B6: 2024 | C6: 5 | D6: OTA 1.7 / 1.7.1 discussions and media evidence of software/interface improvements, including navigation, heating, seat-heating controls, charging-planning refinements, wireless CarPlay, and ADAS-related optimization. | E6: Feature improvements; localization updates; ADAS-related improvement | F6: BYD Atto 3 Forum, 2024; CarExpert, 2024
A7: BYD | B7: 2025 | C7: 4 | D7: OTA 2.0 user evidence and assisted-driving improvement evidence for ATTO 3 after Euro NCAP assessment. | E7: Feature improvements; assisted-driving improvement; localization/interface refinement | F7: BYD Atto 3 Forum, 2025; Euro NCAP, 2025

Sheet ecosystem
A1: core | B1: Meaning
A2: 0 | B2: No/unclear app integration
A3: 1 | B3: Basic app presence
A4: 2 | B4: Remote-control and vehicle-status integration
A5: 3 | B5: Smart ecosystem integration with app, vehicle data, connected services, AI/smart features, or behavioral-data use
A8: Company | B8: Period | C8: Score | D8: Remote control | E8: Smart recommendations | F8: Behavioral/status data | G8: Rationale | H8: Sources
A9: Tesla | B9: 2023Q1 | C9: 3 | D9: Yes | E9: Yes/partial | F9: Yes | G9: Tesla app is deeply connected with vehicle controls, climate, charging/range, charging history/behavior, service diagnostics/location data, software updates, and upgrades. | H9: Tesla app support; local App Radar/app review evidence
A10: Tesla | B10: 2023Q2 | C10: 3 | D10: Yes | E10: Yes/partial | F10: Yes | G10: Tesla app is deeply connected with vehicle controls, climate, charging/range, charging history/behavior, service diagnostics/location data, software updates, and upgrades. | H10: Tesla app support; local App Radar/app review evidence
A11: Tesla | B11: 2023Q3 | C11: 3 | D11: Yes | E11: Yes/partial | F11: Yes | G11: Tesla app is deeply connected with vehicle controls, climate, charging/range, charging history/behavior, service diagnostics/location data, software updates, and upgrades. | H11: Tesla app support; local App Radar/app review evidence
A12: Tesla | B12: 2023Q4 | C12: 3 | D12: Yes | E12: Yes/partial | F12: Yes | G12: Tesla app is deeply connected with vehicle controls, climate, charging/range, charging history/behavior, service diagnostics/location data, software updates, and upgrades. | H12: Tesla app support; local App Radar/app review evidence
A13: Tesla | B13: 2024Q1 | C13: 3 | D13: Yes | E13: Yes/partial | F13: Yes | G13: Tesla app is deeply connected with vehicle controls, climate, charging/range, charging history/behavior, service diagnostics/location data, software updates, and upgrades. | H13: Tesla app support; local App Radar/app review evidence
A14: Tesla | B14: 2024Q2 | C14: 3 | D14: Yes | E14: Yes/partial | F14: Yes | G14: Tesla app is deeply connected with vehicle controls, climate, charging/range, charging history/behavior, service diagnostics/location data, software updates, and upgrades. | H14: Tesla app support; local App Radar/app review evidence
A15: Tesla | B15: 2024Q3 | C15: 3 | D15: Yes | E15: Yes/partial | F15: Yes | G15: Tesla app is deeply connected with vehicle controls, climate, charging/range, charging history/behavior, service diagnostics/location data, software updates, and upgrades. | H15: Tesla app support; local App Radar/app review evidence
A16: Tesla | B16: 2024Q4 | C16: 3 | D16: Yes | E16: Yes/partial | F16: Yes | G16: Tesla app is deeply connected with vehicle controls, climate, charging/range, charging history/behavior, service diagnostics/location data, software updates, and upgrades. | H16: Tesla app support; local App Radar/app review evidence
A17: Tesla | B17: 2025Q1 | C17: 3 | D17: Yes | E17: Yes/partial | F17: Yes | G17: Tesla app is deeply connected with vehicle controls, climate, charging/range, charging history/behavior, service diagnostics/location data, software updates, and upgrades. | H17: Tesla app support; local App Radar/app review evidence
A18: Tesla | B18: 2025Q2 | C18: 3 | D18: Yes | E18: Yes/partial | F18: Yes | G18: Tesla app is deeply connected with vehicle controls, climate, charging/range, charging history/behavior, service diagnostics/location data, software updates, and upgrades. | H18: Tesla app support; local App Radar/app review evidence
A19: Tesla | B19: 2025Q3 | C19: 3 | D19: Yes | E19: Yes/partial | F19: Yes | G19: Tesla app is deeply connected with vehicle controls, climate, charging/range, charging history/behavior, service diagnostics/location data, software updates, and upgrades. | H19: Tesla app support; local App Radar/app review evidence
A20: Tesla | B20: 2025Q4 | C20: 3 | D20: Yes | E20: Yes/partial | F20: Yes | G20: Tesla app is deeply connected with vehicle controls, climate, charging/range, charging history/behavior, service diagnostics/location data, software updates, and upgrades. | H20: Tesla app support; local App Radar/app review evidence
... A32: BYD | B32: 2025Q4 | C32: 2 | D32: Yes | E32: No clear evidence | F32: Yes/vehicle status | G32: BYD app supports remote control and vehicle-status inquiry, but evidence from Germany/Europe shows weaker integration, country differences, and reliability/functionality limits. | H32: BYD AUTO app description; local App Radar/app review/forum evidence

Sheet additional variables
A1: Company | B1: Tesla | F1: BYD | J1: Tesla | N1: BYD | R1: Tesla | V1: BYD
A2: Period | B2: 2023Q1 | C2: 2023Q2 | D2: 2023Q3 | E2: 2023Q4 | F2: 2023Q1 | G2: 2023Q2 | H2: 2023Q3 | I2: 2023Q4 | J2: 2024Q1 | K2: 2024Q2 | L2: 2024Q3 | M2: 2024Q4 | N2: 2024Q1 | O2: 2024Q2 | P2: 2024Q3 | Q2: 2024Q4 | R2: 2025Q1 | S2: 2025Q2 | T2: 2025Q3 | U2: 2025Q4 | V2: 2025Q1 | W2: 2025Q2 | X2: 2025Q3 | Y2: 2025Q4
A3: AI R&D Investment
A4: AI-related patent filed (patents in ADAS, AI chips) | B4: 9 | C4: 13 | D4: 18 | E4: 2 | F4: 12 | G4: 9 | H4: 32 | I4: 29 | J4: 2 | K4: 3 | L4: 3 | M4: 0 | N4: 32 | O4: 50 | P4: 40 | Q4: 31 | R4: 4 | S4: 0 | T4: 2 | U4: 0 | V4: 41 | W4: 48 | X4: 7 | Y4: 0
A5: R&D spending (in million USD) | B5: 771 | C5: 943 | D5: 1161 | E5: 1094 | F5: =F6*0.1455 -> 907.61445 | G5: =G6*0.1455 -> 1105.3198 | H5: =H6*0.1455 -> 1615.5883 | I5: =I6*0.1455 -> 2129.6253 | J5: 1151 | K5: 1074 | L5: 1039 | M5: 1276 | N5: =N6*0.1455 -> 1543.8568 | O5: =O6*0.1455 -> 1310.9696 | P5: =P6*0.1455 -> 1993.1317 | Q5: =Q6*0.1455 -> 2891.8852 | R5: 1409 | S5: 1589 | T5: 1630 | U5: 1783 | V5: =V6*0.1455 -> 2069.4465 | W5: =W6*0.1455 -> 2236.8297 | X5: =X6*0.1455 -> 2059.1305 | Y5: =Y6*0.1455 -> 2070.4214
A6: in RMB mln | F6: 6237.9 | G6: 7596.7 | H6: 11103.7 | I6: 14636.6 | N6: 10610.7 | O6: 9010.1 | P6: 13698.5 | Q6: 19875.5 | V6: 14223 | W6: 15373.4 | X6: 14152.1 | Y6: 14229.7
E7: =SUM(B5:E5) -> 3969 | I7: =SUM(F5:I5) -> 5758.1479 | M7: =SUM(J5:M5) -> 4540 | Q7: =SUM(N5:Q5) -> 7739.8434 | U7: =SUM(R5:U5) -> 6411 | Y7: =SUM(V5:Y5) -> 8435.8281
A9: Sources: | B9: Tesla | F9: BYD
A10: Patent databases export | B10: patent folder | F10: patent folder
A11: companies' reports | B11: Research and development in Statement of operations (around pp. 20-29) | F11: Research and development expenses / 研发费用, Consolidated Income Statement (around pp. 15-18 in q reports, 42-44, 64 interim, 117, 127, 144 in annual).
F12: 1 RMB = 0.1455 USD
A13: BYD Q2/Q3/Q4 values are derived from cumulative H1/9M/FY company-report figures. Tesla values are reported directly in USD millions.

Sheet coding scheme
A1: Qualitative Coding Scheme for User Feedback Analysis
A2: Code | B2: Category | C2: Description | D2: Example Interpretation
A3: USE+ | B3: Perceived Usefulness (Positive) | C3: User expresses that the feature/service is helpful, valuable, or improves experience | D3: “Navigation works great”, “Very useful app”
A4: USE− | B4: Perceived Usefulness (Negative) | C4: User finds the feature/service unnecessary or not beneficial | D4: “Doesn’t add any value”, “Useless feature”
A5: UX+ | B5: Usability / Interface (Positive) | C5: Positive evaluation of ease of use, interface design, or interaction clarity | D5: “Easy to use”, “Clean interface”
A6: UX− | B6: Usability / Interface (Negative) | C6: Complaints about complexity, confusion, or poor interface design | D6: “Hard to use”, “Confusing layout”
A7: REL+ | B7: Reliability / Performance (Positive) | C7: System performs consistently and without errors | D7: “Works smoothly”, “No issues so far”
A8: REL− | B8: Reliability / Performance (Negative) | C8: Bugs, crashes, delays, or inconsistent performance | D8: “App crashes”, “System unreliable”
A9: TRUST+ | B9: Trust & Safety (Positive) | C9: User expresses confidence in system safety or reliability | D9: “I trust this system”, “Feels safe to use”
A10: TRUST− | B10: Trust & Safety (Negative) | C10: Concerns about safety, risk, or lack of trust | D10: “Don't trust autopilot”, “Feels unsafe”
A11: LOC+ | B11: Localization / Context Fit (Positive) | C11: System works well in local conditions (roads, language, regulations) | D11: “Works well in my country”, “Good local adaptation”
A12: LOC− | B12: Localization / Context Fit (Negative) | C12: System poorly adapted to local environment | D12: “Not suitable for local traffic”, “Doesn't support local language well”
A13: DIGI+ | B13: Digital Ecosystem / Connectivity (Positive) | C13: Positive experience with app, connectivity, updates, or integration | D13: “App sync is perfect”, “Updates are smooth”
... A17: AI− | B17: AI Mention (Negative) | C17: Explicit negative mention of AI or intelligent features | D17: “AI system is flawed”
B20: Source: review folders

Sheet coding raw
A1: Case_ID | B1: ID | C1: Company | D1: Market | E1: Platform | F1: Date | G1: Quarter | H1: Review Text (short) | I1: USE+ | J1: USE− | K1: UX+ | L1: UX− | M1: REL+ | N1: REL− | O1: TRUST+ | P1: TRUST− | Q1: LOC+ | R1: LOC− | S1: DIGI+ | T1: DIGI− | U1: ISSUE | V1: AI+ | W1: AI− | X1: Notes
A2: T-AP-001 | B2: 1 | C2: Tesla | D2: China | E2: App Store | F2: 46036 | G2: 2026 Q1 | H2: Widget became blank after update | I2: 0 | J2: 0 | K2: 0 | L2: 1 | M2: 0 | N2: 1 | O2: 0 | P2: 0 | Q2: 0 | R2: 0 | S2: 0 | T2: 0 | U2: 0 | V2: 0 | W2: 0 | X2: update broke feature
A3: T-AP-002 | B3: 2 | C3: Tesla | D3: China | E3: App Store | F3: 45920 | G3: 2025 Q3 | H3: Wants dashcam download + timestamp | I3: 1 | J3: 0 | K3: 0 | L3: 0 | M3: 0 | N3: 0 | O3: 0 | P3: 0 | Q3: 0 | R3: 0 | S3: 1 | T3: 0 | U3: 0 | V3: 0 | W3: 0 | X3: feature request
A4: T-AP-003 | B4: 3 | C4: Tesla | D4: China | E4: App Store | F4: 45844 | G4: 2025 Q3 | H4: Voice assistant weak, poor obstacle detection | I4: 0 | J4: 0 | K4: 0 | L4: 0 | M4: 0 | N4: 1 | O4: 0 | P4: 1 | Q4: 0 | R4: 0 | S4: 0 | T4: 0 | U4: 1 | V4: 0 | W4: 0 | X4: safety + AI expectation
A5: T-AP-004 | B5: 4 | C5: Tesla | D5: China | E5: App Store | F5: 45807 | G5: 2025 Q2 | H5: Slow iteration, bad voice | I5: 0 | J5: 0 | K5: 0 | L5: 1 | M5: 0 | N5: 1 | O5: 0 | P5: 0 | Q5: 0 | R5: 0 | S5: 0 | T5: 0 | U5: 1 | V5: 0 | W5: 0 | X5: strong negative
A6: T-AP-005 | B6: 5 | C6: Tesla | D6: China | E6: App Store | F6: 45682 | G6: 2025 Q1 | H6: Wants charging station info in navigation | I6: 1 | J6: 0 | K6: 0 | L6: 0 | M6: 0 | N6: 0 | O6: 0 | P6: 0 | Q6: 0 | R6: 0 | S6: 1 | T6: 0 | U6: 0 | V6: 0 | W6: 0 | X6: ecosystem request
A7: T-AP-006 | B7: 6 | C7: Tesla | D7: China | E7: App Store | F7: 45639 | G7: 2024 Q4 | H7: Wants more charging stats customization | I7: 1 | J7: 0 | K7: 0 | L7: 0 | M7: 0 | N7: 0 | O7: 0 | P7: 0 | Q7: 0 | R7: 0 | S7: 1 | T7: 0 | U7: 0 | V7: 0 | W7: 0 | X7: feature expansion
A8: T-AP-007 | B8: 7 | C8: Tesla | D8: China | E8: App Store | F8: 45491 | G8: 2024 Q3 | H8: Wants scheduled ventilation | I8: 1 | J8: 0 | K8: 0 | L8: 0 | M8: 0 | N8: 0 | O8: 0 | P8: 0 | Q8: 0 | R8: 0 | S8: 1 | T8: 0 | U8: 0 | V8: 0 | W8: 0 | X8: usability improvement
A9: T-AP-008 | B9: 8 | C9: Tesla | D9: China | E9: App Store | F9: 45349 | G9: 2024 Q1 | H9: Wants charging availability info | I9: 1 | J9: 0 | K9: 0 | L9: 0 | M9: 0 | N9: 0 | O9: 0 | P9: 0 | Q9: 0 | R9: 0 | S9: 1 | T9: 0 | U9: 0 | V9: 0 | W9: 0 | X9: infrastructure link
A10: T-AP-009 | B10: 9 | C10: Tesla | D10: China | E10: App Store | F10: 45318 | G10: 2024 Q1 | H10: Wants privacy protection | I10: 0 | J10: 0 | K10: 0 | L10: 0 | M10: 0 | N10: 0 | O10: 0 | P10: 1 | Q10: 0 | R10: 0 | S10: 0 | T10: 0 | U10: 0 | V10: 0 | W10: 0 | X10: privacy concern
A11: T-AP-010 | B11: 10 | C11: Tesla | D11: China | E11: App Store | F11: 45284 | G11: 2023 Q4 | H11: Slow connection, poor scheduling logic | I11: 0 | J11: 1 | K11: 0 | L11: 1 | M11: 0 | N11: 1 | O11: 0 | P11: 0 | Q11: 0 | R11: 0 | S11: 0 | T11: 1 | U11: 0 | V11: 0 | W11: 0 | X11: connectivity issues
A12: T-AP-011 | B12: 11 | C12: Tesla | D12: China | E12: App Store | F12: 45283 | G12: 2023 Q4 | H12: Charging stations data is limited, wants improvement | I12: 1 | J12: 0 | K12: 0 | L12: 0 | M12: 0 | N12: 0 | O12: 0 | P12: 0 | Q12: 0 | R12: 0 | S12: 1 | T12: 0 | U12: 0 | V12: 0 | W12: 0 | X12: infrastructure link
A13: T-AP-012 | B13: 12 | C13: Tesla | D13: China | E13: App Store | F13: 45222 | G13: 2023 Q4 | H13: Supercharger display is accurate, navigation should show conditions more precisely | I13: 1 | J13: 0 | K13: 0 | L13: 0 | M13: 1 | N13: 1 | O13: 0 | P13: 0 | Q13: 0 | R13: 0 | S13: 0 | T13: 0 | U13: 0 | V13: 0 | W13: 0 | X13: infrastructure link
... A43: T-PL-042 | B43: 42 | C43: Tesla | D43: China | E43: Play Store | F43: 45372 | G43: 2024 Q1 | H43: Wants unified version | I43: 1 | J43: 0 | K43: 0 | L43: 0 | M43: 0 | N43: 0 | O43: 0 | P43: 0 | Q43: 0 | R43: 1 | S43: 1 | T43: 0 | U43: 0 | V43: 0 | W43: 0 | X43: request
A44: T-PL-043 | B44: 43 | C44: Tesla | D44: China | E44: Play Store | F44: 45356 | G44: 2024 Q1 | H44: CN users ignored, no fixes | I44: 0 | J44: 1 | K44: 0 | L44: 0 | M44: 0 | N44: 1 | O44: 0 | P44: 0 | Q44: 0 | R44: 1 | S44: 0 | T44: 1 | U44: 0 | V44: 0 | W44: 0
A45: T-PL-044 | B45: 44 | C45: Tesla | D45: China | E45: Play Store | F45: 45267 | G45: 2023 Q4 | H45: China app maps drift, Play version black map, must reinstall CN version | I45: 0 | J45: 1 | K45: 0 | L45: 0 | M45: 0 | N45: 1 | O45: 0 | P45: 0 | Q45: 0 | R45: 1 | S45: 0 | T45: 1 | U45: 1 | V45: 0 | W45: 0 | X45: severe localization/app failure
A46: T-PL-045 | B46: 45 | C46: Tesla | D46: China | E46: Play Store | F46: 45254 | G46: 2023 Q4 | H46: Could see location before, later versions cannot | I46: 0 | J46: 0 | K46: 0 | L46: 0 | M46: 0 | N46: 1 | O46: 0 | P46: 0 | Q46: 0 | R46: 0 | S46: 0 | T46: 1 | U46: 0 | V46: 0 | W46: 0 | X46: functionality loss
A47: T-PL-046 | B47: 46 | C47: Tesla | D47: China | E47: Play Store | F47: 45248 | G47: 2023 Q4 | H47: Location no longer visible, even with workaround | I47: 0 | J47: 0 | K47: 0 | L47: 0 | M47: 0 | N47: 1 | O47: 0 | P47: 0 | Q47: 0 | R47: 1 | S47: 0 | T47: 1 | U47: 0 | V47: 0 | W47: 0 | X47: recurring map/location failure
A48: T-PL-047 | B48: 47 | C48: Tesla | D48: China | E48: Play Store | F48: 45212 | G48: 2023 Q4 | H48: Auto-updated app breaks maps again, black screen | I48: 0 | J48: 0 | K48: 0 | L48: 1 | M48: 0 | N48: 1 | O48: 0 | P48: 0 | Q48: 0 | R48: 1 | S48: 0 | T48: 1 | U48: 0 | V48: 0 | W48: 0 | X48: update + map failure
A49: T-PL-048 | B49: 48 | C49: Tesla | D49: China | E49: Play Store | F49: 45079 | G49: 2023 Q2 | H49: Wants light mode; dark mode hard to see in sunlight | I49: 1 | J49: 0 | K49: 0 | L49: 1 | M49: 0 | N49: 0 | O49: 0 | P49: 0 | Q49: 0 | R49: 0 | S49: 0 | T49: 0 | U49: 0 | V49: 0 | W49: 0 | X49: design/usability request
A50: T-PL-049 | B50: 49 | C50: Tesla | D50: China | E50: Play Store | F50: 45068 | G50: 2023 Q2 | H50: Wants map provider choice to solve display issue after updates | I50: 1 | J50: 0 | K50: 0 | L50: 0 | M50: 0 | N50: 1 | O50: 0 | P50: 0 | Q50: 0 | R50: 1 | S50: 1 | T50: 0 | U50: 0 | V50: 0 | W50: 0 | X50: feature request tied to localization
A51: T-AU-050 | B51: Thread 113884059 | C51: Tesla | D51: China | E51: Autohome Forum | F51: 46009 | G51: 2025 Q4 | H51: “The overseas version has automatic shifting, but the domestic version is not equipped with it yet” (“国外版本有自动换挡功能，国内版本暂未配备”); “After driving with screen shifting for more than 1,000 km, I have adapted, but I still prefer a physical gear lever” (“屏幕换挡开了1000多公里后已适应，但仍更喜欢物理换挡杆”); “The brake pedal feel is simulated by the computer… the current simulation effect is average, but it can be optimized later through OTA” (“刹车踏板脚感由电脑通过弹簧、阻尼片模拟…目前模拟效果一般，但后续可通过OTA优化”); “The car-machine chip is still AMD; although it has not been updated for many years, it runs smoothly” (“车机芯片：依旧是AMD芯片，虽多年未更新，但运行流畅”); “When the turn signal is activated, the central screen automatically enlarges the corresponding side image, making lane changing convenient” (“打开后打转向灯，中控屏会自动放大对应侧画面，方便变道”) | I51: 1 | J51: 1 | K51: 0 | L51: 1 | M51: 0 | N51: 1 | O51: 0 | P51: 0 | Q51: 0 | R51: 1 | S51: 1 | T51: 0 | U51: 0 | V51: 0 | W51: 0
A52: T-AU-051 | B52: Thread 110684131 | C52: Tesla | D52: China | E52: Autohome Forum | F52: 45703 | G52: 2025 Q1 | H52: “Xiaomi is rapidly rising with the posture of ‘king of cost performance’” (“小米则以‘性价比之王’的姿态快速崛起”); Xiaomi’s intelligent driving is free; lidar + Orin chip combination is stronger in complex-scenario recognition” (“小米：智驾免费，激光雷达+Orin芯片组合在复杂场景识别更强”); “FSD is paid, and domestic functions are limited” (“FSD（收费3.2万，国内功能受限）”); “Tesla’s FSD technology is globally leading, but domestic functions are limited and require a high-price purchase” (“特斯拉：FSD技术全球领先……但国内功能受限且需高价购买”); “Choose Tesla if you pursue brand aura, long range, mature autonomous driving, and can accept a higher premium” (“选特斯拉：追求品牌光环、长续航、成熟自动驾驶，且能接受较高溢价”) | I52: 1 | J52: 1 | K52: 0 | L52: 0 | M52: 0 | N52: 1 | O52: 0 | P52: 0 | Q52: 0 | R52: 1 | S52: 0 | T52: 1 | U52: 1 | V52: 0 | W52: 0
A53: T-AU-052 | B53: Thread 107606189 | C53: Tesla | D53: China | E53: Autohome Forum | F53: 45342 | G53: 2024 Q1 | H53: “If I had not been driving attentively, there might have been a serious accident” (“如果不是我专心开车，可能就会有严重事故”); “Using AP on the highway, I was driving normally, with both hands on the steering wheel and concentrating” (“高速上使用AP正常行驶时，双手正常握方向盘，聚精会神开车”); “AP suddenly exited… after locking the car for a few minutes and restarting, it returned to normal” (“AP直接退出……锁车几分钟重启车子又正常了”); “Never overly trust the system, and do not mythologize how powerful Tesla FSD is” (“千万不要过度信赖系统，也不要迷信、魔化特斯拉FSD多牛逼”); “Computers crash and have bugs; Tesla is the same” (“电脑都有死机，出bug的时候，特斯拉也一样”) | I53: 0 | J53: 0 | K53: 0 | L53: 0 | M53: 0 | N53: 1 | O53: 0 | P53: 1 | Q53: 0 | R53: 0 | S53: 0 | T53: 0 | U53: 1 | V53: 0 | W53: 0
A54: T-AU-053 | B54: Thread 110795738 | C54: Tesla | D54: China | E54: Autohome Forum | F54: 45714 | G54: 2025 Q1 | H54: “Chinese roads’ complexity is far beyond what a few videos can cover” (“中国道路的复杂性远非几段录像所能涵盖”); “FSD mistakenly identified a non-motorized lane as a side road, forcing the driver to take over” (“FSD误将非机动车道识别为辅路，导致驾驶员被迫接管”); “Problems occurred frequently, such as mistakenly entering bus lanes, being overly ‘polite’ at intersections, and confused automatic gear-shifting logic in parking lots” (“误入公交车道、路口过度‘礼貌’导致通行效率低下、停车场自动挂挡逻辑混乱等问题频发”); “Huawei ADS 3.0 and XPeng map-free NOA have already achieved higher-level capabilities” (“华为ADS 3.0、小鹏无图NOA等本土方案已实现更高阶能力”);“No matter what form intelligent driving takes, at present driving is still human-centered” (“不论什么形式的智驾，目前还是以人为主的驾驶”) | I54: 0 | J54: 1 | K54: 0 | L54: 0 | M54: 0 | N54: 1 | O54: 0 | P54: 1 | Q54: 0 | R54: 1 | S54: 0 | T54: 0 | U54: 0 | V54: 0 | W54: 0
A55: T-AU-054 | B55: Thread 110825872 | C55: Tesla | D55: China | E55: Autohome Forum | F55: 45716 | G55: 2025 Q1 | H55: “Although I still do not dare to fully let FSD drive by itself” (“虽然我还是不敢完全放手让FSD自己开”); “Enhanced automatic parking is indeed reliable; even a parking space with 2.3 m between basement pillars is no problem” (“但增强版自动泊车确实靠谱，地库立柱间距2.3米的车位也完全没问题”); “Supercharger network coverage…” (“超充网络覆盖率…”); “Enhanced automatic parking is indeed reliable; even a parking space with 2.3 m between basement pillars is no problem” (“增强版自动泊车确实靠谱，地库立柱间距2.3米的车位也完全没问题”) | I55: 1 | J55: 0 | K55: 0 | L55: 0 | M55: 1 | N55: 1 | O55: 0 | P55: 1 | Q55: 0 | R55: 0 | S55: 1 | T55: 0 | U55: 0 | V55: 0 | W55: 0
A56: T-AU-055 | B56: Thread 110559634 | C56: Tesla | D56: China | E56: Autohome Forum | F56: 45687 | G56: 2025 Q1 | H56: “The actual experience improvement is not as exaggerated as advertised, and some functions still need improvement” (“实际体验提升并没有宣传的那么夸张，部分功能还有待完善”); “Autonomous driving is still assisted driving; it cannot be fully relied on, and we must stay alert at all times” (“自动驾驶功能，现在还是辅助驾驶，不能完全依赖……得时刻保持警惕”); “The update brings some significant improvements, but this does not mean it is perfect” (“更新带来了一些显著的改进，但这并不代表它就完美无缺”); “XPeng’s XPILOT performs relatively well on urban roads; NIO’s NOP is relatively stable on highways” (“小鹏的XPILOT在城市道路上的表现相对出色……蔚来的NOP则在高速路况下比较稳定”); “Autonomous-driving technology still needs time to develop” (“自动驾驶技术的发展，还需要时间”) | I56: 1 | J56: 0 | K56: 0 | L56: 0 | M56: 0 | N56: 1 | O56: 0 | P56: 1 | Q56: 0 | R56: 0 | S56: 0 | T56: 0 | U56: 1 | V56: 0 | W56: 0
A57: T-AU-056 | B57: Thread 110212244 | C57: Tesla | D57: China | E57: Autohome Forum | F57: 45653 | G57: 2024 Q4 | H57: “Do not set expectations too high” (“不要期望值太高了”); “No matter how advanced autonomous driving is, it still cannot leave the human” (“再高级的自动驾驶也不能离开人”); “Intelligent driving is divided only into Huawei and other rubbish” (“智驾只分华为和其他垃圾”); “Tesla needs to ensure compatibility and stability in the Chinese market” (“特斯拉需要确保新版本在中国市场的兼容性和稳定性”) | I57: 0 | J57: 0 | K57: 0 | L57: 0 | M57: 0 | N57: 1 | O57: 0 | P57: 1 | Q57: 0 | R57: 0 | S57: 0 | T57: 0 | U57: 1 | V57: 0 | W57: 0
A59: Case_ID | B59: ID | C59: Company | D59: Market | E59: Platform | F59: Date | G59: Quarter | H59: Review Text (short) | I59: USE+ | J59: USE− | K59: UX+ | L59: UX− | M59: REL+ | N59: REL− | O59: TRUST+ | P59: TRUST− | Q59: LOC+ | R59: LOC− | S59: DIGI+ | T59: DIGI− | U59: ISSUE | V59: AI+ | W59: AI− | X59: Notes
A60: B-AP-057 | B60: 1 | C60: BYD | D60: Germany | E60: App Store | F60: 46090 | G60: 2026 Q1 | H60: Missing features (charging, range, roof) | I60: 1 | J60: 0 | K60: 0 | L60: 0 | M60: 0 | N60: 0 | O60: 0 | P60: 0 | Q60: 0 | R60: 0 | S60: 1 | T60: 0 | U60: 0 | V60: 0 | W60: 0
A61: B-AP-058 | B61: 2 | C61: BYD | D61: Germany | E61: App Store | F61: 46071 | G61: 2026 Q1 | H61: Update broke app, network errors | I61: 0 | J61: 0 | K61: 0 | L61: 0 | M61: 0 | N61: 1 | O61: 0 | P61: 0 | Q61: 0 | R61: 0 | S61: 0 | T61: 1 | U61: 1 | V61: 0 | W61: 0
A62: B-AP-059 | B62: 3 | C62: BYD | D62: Germany | E62: App Store | F62: 46070 | G62: 2026 Q1 | H62: Bad UI, cluttered, missing features | I62: 1 | J62: 0 | K62: 1 | L62: 0 | M62: 0 | N62: 0 | O62: 0 | P62: 0 | Q62: 0 | R62: 0 | S62: 1 | T62: 0 | U62: 1 | V62: 0 | W62: 0
A63: B-AP-060 | B63: 4 | C63: BYD | D63: Germany | E63: App Store | F63: 46054 | G63: 2026 Q1 | H63: Good but limited users (accounts issue) | I63: 1 | J63: 0 | K63: 0 | L63: 0 | M63: 0 | N63: 0 | O63: 0 | P63: 0 | Q63: 0 | R63: 0 | S63: 0 | T63: 1 | U63: 1 | V63: 0 | W63: 0
A64: B-AP-061 | B64: 5 | C64: BYD | D64: Germany | E64: App Store | F64: 46041 | G64: 2026 Q1 | H64: Works but missing Apple Watch | I64: 1 | J64: 0 | K64: 0 | L64: 0 | M64: 0 | N64: 0 | O64: 0 | P64: 0 | Q64: 0 | R64: 0 | S64: 0 | T64: 0 | U64: 0 | V64: 0 | W64: 0
A65: B-AP-062 | B65: 6 | C65: BYD | D65: Germany | E65: App Store | F65: 46035 | G65: 2026 Q1 | H65: Works well | I65: 1 | J65: 0 | K65: 0 | L65: 0 | M65: 0 | N65: 0 | O65: 0 | P65: 0 | Q65: 0 | R65: 0 | S65: 0 | T65: 0 | U65: 0 | V65: 0 | W65: 0
A66: B-AP-063 | B66: 7 | C66: BYD | D66: Germany | E66: App Store | F66: 46028 | G66: 2026 Q1 | H66: Notifications not working | I66: 0 | J66: 0 | K66: 0 | L66: 0 | M66: 0 | N66: 1 | O66: 0 | P66: 0 | Q66: 0 | R66: 0 | S66: 0 | T66: 1 | U66: 0 | V66: 0 | W66: 0
A67: B-AP-064 | B67: 8 | C67: BYD | D67: Germany | E67: App Store | F67: 45967 | G67: 2025 Q4 | H67: Missing alarms, worse than Hyundai | I67: 0 | J67: 1 | K67: 0 | L67: 0 | M67: 0 | N67: 0 | O67: 0 | P67: 0 | Q67: 0 | R67: 0 | S67: 0 | T67: 0 | U67: 0 | V67: 0 | W67: 0
A68: B-AP-065 | B68: 9 | C68: BYD | D68: Germany | E68: App Store | F68: 45959 | G68: 2025 Q4 | H68: Poor UX logic, slow interaction | I68: 0 | J68: 0 | K68: 1 | L68: 0 | M68: 0 | N68: 0 | O68: 0 | P68: 0 | Q68: 0 | R68: 0 | S68: 0 | T68: 0 | U68: 0 | V68: 0 | W68: 0
A69: B-AP-066 | B69: 10 | C69: BYD | D69: Germany | E69: App Store | F69: 45946 | G69: 2025 Q4 | H69: Works but seat heating unreliable | I69: 0 | J69: 0 | K69: 0 | L69: 0 | M69: 0 | N69: 1 | O69: 0 | P69: 0 | Q69: 0 | R69: 0 | S69: 0 | T69: 0 | U69: 0 | V69: 0 | W69: 0
A70: B-AP-067 | B70: 11 | C70: BYD | D70: Germany | E70: App Store | F70: 45904 | G70: 2025 Q3 | H70: Basic functions, no dark mode/widgets issues | I70: 0 | J70: 0 | K70: 0 | L70: 1 | M70: 0 | N70: 0 | O70: 0 | P70: 0 | Q70: 0 | R70: 0 | S70: 0 | T70: 1 | U70: 1 | V70: 0 | W70: 0
A71: B-AP-068 | B71: 12 | C71: BYD | D71: Germany | E71: App Store | F71: 45794 | G71: 2025 Q2 | H71: Charging stop not working | I71: 0 | J71: 0 | K71: 0 | L71: 0 | M71: 0 | N71: 1 | O71: 0 | P71: 0 | Q71: 0 | R71: 0 | S71: 0 | T71: 0 | U71: 0 | V71: 0 | W71: 0
... A146: B-GO-143 | B146: 97855 | C146: BYD | D146: Germany | E146: GoingElectric | F146: 45859 | G146: 2025 Q3 | H146: “If it initiates pointless strong braking in completely harmless situations, then it is not good” (“wenn er aber immer und in vollkommen ungefährlichen Situationen eine sinnlose starke Bremsung einleitet dann ist es nicht gut”); “In such cases, the assistant is then usually switched off by drivers” (“In solchen Fällen wird der Assistent dann meistens von den Fahrern abgeschaltet”) | I146: 0 | J146: 1 | K146: 0 | L146: 0 | M146: 0 | N146: 1 | O146: 0 | P146: 1 | Q146: 0 | R146: 0 | S146: 0 | T146: 0 | U146: 1 | V146: 0 | W146: 0
A147: B-GO-144 | B147: 90714 | C147: BYD | D147: Germany | E147: GoingElectric | F147: 45258 | G147: 2023 Q4 | H147: “Very limited function of the head-up display” (“die äußerst begrenzte Funktion des Headup Displays”); “For example, the navigation system cannot be displayed/integrated” (“zum Beispiel kann man das Navigationssystem nicht einspielen”); “In borderline situations, the assistance systems seem to be overwhelmed” (“in Grenzsituationen die Assistenzsysteme überfordert”) | I147: 0 | J147: 1 | K147: 0 | L147: 0 | M147: 0 | N147: 1 | O147: 0 | P147: 1 | Q147: 0 | R147: 1 | S147: 0 | T147: 1 | U147: 0 | V147: 0 | W147: 0 | X147: system functionality limitation interface integration problem
A148: B-GO-145 | B148: 97478 | C148: BYD | D148: Germany | E148: GoingElectric | F148: 45786 | G148: 2025 Q2 | H148: “The EU version partly matched the China version, then again 3.90 m was stated” (“die Länge der EU Version teilweise mit der China Version überein gestimmt hat… Dann wieder wurden 3,90m angegeben”); “The stupid blink-blink, beep-beep nonsense” (“der blödsinnige blink,blink, piep,piep Quatsch”); “360-degree camera” (“360 Grad Kamera”) | I148: 1 | J148: 1 | K148: 0 | L148: 1 | M148: 0 | N148: 0 | O148: 0 | P148: 0 | Q148: 0 | R148: 1 | S148: 1 | T148: 0 | U148: 0 | V148: 0 | W148: 0
A149: B-GO-146 | B149: 93267 | C149: BYD | D149: Germany | E149: GoingElectric | F149: 45446 | G149: 2024 Q2 | H149: “The software in its current state cannot keep up with the Model 3 or German cars” (“Einzig die Software kann in aktuellem Zustand weder mit dem Model 3 noch mit den deutschen Autos mithalten”); “The software is definitely still expandable” (“Die Software ist in jedem Fall noch ausbaufähig”); “No charger route planning” (“keine Laderoutenplanung”); “No SOC information at the destination” (“keine SOC-Angaben am Ziel”); “Some translation errors” (“einige Übersetzungsfehler”); “First attempts to work with the Chinese SDK lead to immediate crashes” (“erste paar Versuche vs chinesische SDK zu arbeiten führt zu sofortige Abstürze”) | I149: 0 | J149: 1 | K149: 0 | L149: 0 | M149: 0 | N149: 1 | O149: 0 | P149: 0 | Q149: 0 | R149: 0 | S149: 0 | T149: 1 | U149: 0 | V149: 0 | W149: 0
A150: B-GO-147 | B150: 85240 | C150: BYD | D150: Germany | E150: GoingElectric | F150: 45345 | G150: 2024 Q2 | H150: “I rate the software status as really bad” (“Richtig schlecht bewerte ich … den Softwarestand”); “Lane-keeping assistant without function” (“Spurhalteassistent ohne Funktion”); “Often pointless warnings in the display” (“Oft sinnlose Warnungen im Display”); “Speed recognition unreliable and much worse than in the i3” (“Geschwindigkeitserkennung unzuverlässig und wesentlich schlechter als im i3”); “A bug that came with one of the last updates” (“ein Bug der mit einem der letzten Updates kam”) | I150: 0 | J150: 0 | K150: 0 | L150: 0 | M150: 0 | N150: 1 | O150: 0 | P150: 1 | Q150: 0 | R150: 0 | S150: 0 | T150: 1 | U150: 0 | V150: 0 | W150: 0
A151: B-GO-148 | B151: 86577 | C151: BYD | D151: Germany | E151: GoingElectric | F151: 45029 | G151: 2023 Q2 | H151: “Unfortunately, completely unusable lane-keeping assistant” (“leider völlig unbrauchbaren Spurhalteassistent”); “I could less easily overlook this in practice” (“darüber könnte ich in der Praxis weniger hinwegsehen”); “I would switch off the lane-keeping assistant” (“Den Spurhalteassistenten würde ich abschalten”); “The Leaf can do that relatively well” (“Der Leaf kann das relativ gut”) | I151: 0 | J151: 1 | K151: 0 | L151: 0 | M151: 0 | N151: 1 | O151: 0 | P151: 1 | Q151: 0 | R151: 0 | S151: 0 | T151: 0 | U151: 0 | V151: 0 | W151: 0
A152: B-GO-149 | B152: 97481 | C152: BYD | D152: Germany | E152: GoingElectric | F152: 45786 | G152: 2025 Q2 | H152: “I would not be happy with BYD software” (“Ich würde damit nicht glücklich werden”); “The infotainment system in the XPeng is much more mature” (“das Infotainment System im Xpeng ist für mich wesentlich erwachsener”); “Less bing-bonging, less disturbing” (“weniger bingeln und bongeln, weniger störend”); “Not overloaded with information, not so quickly built-in” (“wirkt nicht überladen mit Info, nicht so ‘schnell reingebaut’”) | I152: 0 | J152: 0 | K152: 0 | L152: 1 | M152: 0 | N152: 1 | O152: 0 | P152: 0 | Q152: 0 | R152: 0 | S152: 0 | T152: 1 | U152: 1 | V152: 0 | W152: 0
A153: B-GO-150 | B153: 89186 | C153: BYD | D153: Germany | E153: GoingElectric | F153: 45167 | G153: 2023 Q3 | H153: “DAB+ keeps freezing or turns off” (“ständig hängt sich das DAB+ auf bzw. geht aus”); “The app simply crashes after a few seconds” (“Die App stürzt nach wenigen Sekunden einfach ab”); “The first vehicle only had the problem after the update… after that, DAB+ was no longer really usable continuously” (“Das erste Fahrzeug hatte das Problem erst nach dem Update… Danach war nicht wirklich mehr DAB+ durchgehend nutzbar”); “Localization involves more than just translating the infotainment” (“Zur Lokalisierung gehört halt mehr, als nur das Infotainment zu übersetzen”); “We manually installed the update to have a German GUI” (“Das Update haben wir auch da manuell installiert, um eine deutsche GUI zu haben”) | I153: 0 | J153: 0 | K153: 0 | L153: 0 | M153: 0 | N153: 1 | O153: 0 | P153: 0 | Q153: 0 | R153: 1 | S153: 0 | T153: 1 | U153: 1 | V153: 0 | W153: 0
A154: B-GO-151 | B154: 85919 | C154: BYD | D154: Germany | E154: GoingElectric | F154: 44997 | G154: 2023 Q2 | H154: “Is your Atto already capable of German language in speech and writing?” (“Ist euer Atto schon der deutschen Sprache in Wort und Schrift mächtig?”); “It is English” (“Ist Englisch”); “It constantly forgets certain settings” (“er ständig gewisse Einstellungen vergisst”); “They still need to work on the software” (“an der Software … müssen sie noch arbeiten”); “Menus and navigation finally also in German” (“Menüs und Navigation jetzt endlich auch in Deutsch!”) | I154: 0 | J154: 0 | K154: 0 | L154: 1 | M154: 0 | N154: 1 | O154: 0 | P154: 0 | Q154: 1 | R154: 1 | S154: 1 | T154: 1 | U154: 0 | V154: 0 | W154: 0
A155: B-GO-152 | B155: 100391 | C155: BYD | D155: Germany | E155: GoingElectric | F155: 46095 | G155: 2026 Q1 | H155: “After an OTA update, the infotainment no longer starts” (“Nach einem OTA Update startet das Infotainment nicht mehr”); “The central display keeps restarting” (“das Zentraldisplay startet immer neu”); “It restarts, but the error remains” (“Es startet zwar neu, aber der Fehler bleibt bestehen”); “Then two updates were installed — no success” (“Dann 2 Updates aufgespielt, kein Erfolg”); “Cannot set anything, no heating, no navigation, nothing at all” (“Kann auch rein gar nichts einstellen, keine Heizung, kein Navi, rein gar nichts”) | I155: 0 | J155: 1 | K155: 0 | L155: 0 | M155: 0 | N155: 1 | O155: 0 | P155: 0 | Q155: 0 | R155: 0 | S155: 0 | T155: 1 | U155: 0 | V155: 0 | W155: 0

Sheet coding count
A1: Case_ID | B1: ID | C1: Company | D1: Platform | E1: Period | F1: Review Text (short) | G1: USE+ | H1: USE− | I1: UX+ | J1: UX− | K1: REL+ | L1: REL− | M1: TRUST+ | N1: TRUST− | O1: LOC+ | P1: LOC− | Q1: DIGI+ | R1: DIGI− | S1: ISSUE | T1: AI+ | U1: AI−
A2: T-AP-001 | B2: 1 | C2: Tesla | D2: App Store | E2: 2026 Q1 | F2: Widget became blank after update | G2: 0 | H2: 0 | I2: 0 | J2: 1 | K2: 0 | L2: 1 | M2: 0 | N2: 0 | O2: 0 | P2: 0 | Q2: 0 | R2: 0 | S2: 0 | T2: 0 | U2: 0
A3: T-AP-002 | B3: 2 | C3: Tesla | D3: App Store | E3: 2025 Q3 | F3: Wants dashcam download + timestamp | G3: 1 | H3: 0 | I3: 0 | J3: 0 | K3: 0 | L3: 0 | M3: 0 | N3: 0 | O3: 0 | P3: 0 | Q3: 1 | R3: 0 | S3: 0 | T3: 0 | U3: 0
A4: T-AP-003 | B4: 3 | C4: Tesla | D4: App Store | E4: 2025 Q3 | F4: Voice assistant weak, poor obstacle detection | G4: 0 | H4: 0 | I4: 0 | J4: 0 | K4: 0 | L4: 1 | M4: 0 | N4: 1 | O4: 0 | P4: 0 | Q4: 0 | R4: 0 | S4: 1 | T4: 0 | U4: 0
A5: T-AP-004 | B5: 4 | C5: Tesla | D5: App Store | E5: 2025 Q2 | F5: Slow iteration, bad voice | G5: 0 | H5: 0 | I5: 0 | J5: 1 | K5: 0 | L5: 1 | M5: 0 | N5: 0 | O5: 0 | P5: 0 | Q5: 0 | R5: 0 | S5: 1 | T5: 0 | U5: 0
A6: T-AP-005 | B6: 5 | C6: Tesla | D6: App Store | E6: 2025 Q1 | F6: Wants charging station info in navigation | G6: 1 | H6: 0 | I6: 0 | J6: 0 | K6: 0 | L6: 0 | M6: 0 | N6: 0 | O6: 0 | P6: 0 | Q6: 1 | R6: 0 | S6: 0 | T6: 0 | U6: 0
A7: T-AP-006 | B7: 6 | C7: Tesla | D7: App Store | E7: 2024 Q4 | F7: Wants more charging stats customization | G7: 1 | H7: 0 | I7: 0 | J7: 0 | K7: 0 | L7: 0 | M7: 0 | N7: 0 | O7: 0 | P7: 0 | Q7: 1 | R7: 0 | S7: 0 | T7: 0 | U7: 0
A8: T-AP-007 | B8: 7 | C8: Tesla | D8: App Store | E8: 2024 Q3 | F8: Wants scheduled ventilation | G8: 1 | H8: 0 | I8: 0 | J8: 0 | K8: 0 | L8: 0 | M8: 0 | N8: 0 | O8: 0 | P8: 0 | Q8: 1 | R8: 0 | S8: 0 | T8: 0 | U8: 0
A9: T-AP-008 | B9: 8 | C9: Tesla | D9: App Store | E9: 2024 Q1 | F9: Wants charging availability info | G9: 1 | H9: 0 | I9: 0 | J9: 0 | K9: 0 | L9: 0 | M9: 0 | N9: 0 | O9: 0 | P9: 0 | Q9: 1 | R9: 0 | S9: 0 | T9: 0 | U9: 0
A10: T-AP-009 | B10: 9 | C10: Tesla | D10: App Store | E10: 2024 Q1 | F10: Wants privacy protection | G10: 0 | H10: 0 | I10: 0 | J10: 0 | K10: 0 | L10: 0 | M10: 0 | N10: 1 | O10: 0 | P10: 0 | Q10: 0 | R10: 0 | S10: 0 | T10: 0 | U10: 0
A11: T-AP-010 | B11: 10 | C11: Tesla | D11: App Store | E11: 2023 Q4 | F11: Slow connection, poor scheduling logic | G11: 0 | H11: 1 | I11: 0 | J11: 1 | K11: 0 | L11: 1 | M11: 0 | N11: 0 | O11: 0 | P11: 0 | Q11: 0 | R11: 1 | S11: 0 | T11: 0 | U11: 0
A12: T-AP-011 | B12: 11 | C12: Tesla | D12: App Store | E12: 2023 Q4 | F12: Charging stations data is limited, wants improvement | G12: 1 | H12: 0 | I12: 0 | J12: 0 | K12: 0 | L12: 0 | M12: 0 | N12: 0 | O12: 0 | P12: 0 | Q12: 1 | R12: 0 | S12: 0 | T12: 0 | U12: 0
A13: T-AP-012 | B13: 12 | C13: Tesla | D13: App Store | E13: 2023 Q4 | F13: Supercharger display is accurate, navigation should show conditions more precisely | G13: 1 | H13: 0 | I13: 0 | J13: 0 | K13: 1 | L13: 1 | M13: 0 | N13: 0 | O13: 0 | P13: 0 | Q13: 0 | R13: 0 | S13: 0 | T13: 0 | U13: 0
... A57: T-AU-056 | B57: 110212244 | C57: Tesla | D57: Autohome Forum | E57: 2024 Q4 | F57: China rollout expectations limited, autonomous driving still needs human control, Huawei viewed as stronger, stability in China still needed | G57: 0 | H57: 0 | I57: 0 | J57: 0 | K57: 0 | L57: 1 | M57: 0 | N57: 1 | O57: 0 | P57: 0 | Q57: 0 | R57: 0 | S57: 1 | T57: 0 | U57: 0
A60: Case_ID | B60: ID | C60: Company | D60: Platform | E60: Period | F60: Review Text (short) | G60: USE+ | H60: USE− | I60: UX+ | J60: UX− | K60: REL+ | L60: REL− | M60: TRUST+ | N60: TRUST− | O60: LOC+ | P60: LOC− | Q60: DIGI+ | R60: DIGI− | S60: ISSUE | T60: AI+ | U60: AI−
A61: B-AP-057 | B61: 1 | C61: BYD | D61: App Store | E61: 2026 Q1 | F61: Missing features (charging, range, roof) | G61: 1 | H61: 0 | I61: 0 | J61: 0 | K61: 0 | L61: 0 | M61: 0 | N61: 0 | O61: 0 | P61: 0 | Q61: 1 | R61: 0 | S61: 0 | T61: 0 | U61: 0
A62: B-AP-058 | B62: 2 | C62: BYD | D62: App Store | E62: 2026 Q1 | F62: Update broke app, network errors | G62: 0 | H62: 0 | I62: 0 | J62: 0 | K62: 0 | L62: 1 | M62: 0 | N62: 0 | O62: 0 | P62: 0 | Q62: 0 | R62: 1 | S62: 1 | T62: 0 | U62: 0
A63: B-AP-059 | B63: 3 | C63: BYD | D63: App Store | E63: 2026 Q1 | F63: Bad UI, cluttered, missing features | G63: 1 | H63: 0 | I63: 1 | J63: 0 | K63: 0 | L63: 0 | M63: 0 | N63: 0 | O63: 0 | P63: 0 | Q63: 1 | R63: 0 | S63: 1 | T63: 0 | U63: 0
A64: B-AP-060 | B64: 4 | C64: BYD | D64: App Store | E64: 2026 Q1 | F64: Good but limited users (accounts issue) | G64: 1 | H64: 0 | I64: 0 | J64: 0 | K64: 0 | L64: 0 | M64: 0 | N64: 0 | O64: 0 | P64: 0 | Q64: 0 | R64: 1 | S64: 1 | T64: 0 | U64: 0
A65: B-AP-061 | B65: 5 | C65: BYD | D65: App Store | E65: 2026 Q1 | F65: Works but missing Apple Watch | G65: 1 | H65: 0 | I65: 0 | J65: 0 | K65: 0 | L65: 0 | M65: 0 | N65: 0 | O65: 0 | P65: 0 | Q65: 0 | R65: 0 | S65: 0 | T65: 0 | U65: 0
A66: B-AP-062 | B66: 6 | C66: BYD | D66: App Store | E66: 2026 Q1 | F66: Works well | G66: 1 | H66: 0 | I66: 0 | J66: 0 | K66: 0 | L66: 0 | M66: 0 | N66: 0 | O66: 0 | P66: 0 | Q66: 0 | R66: 0 | S66: 0 | T66: 0 | U66: 0
A67: B-AP-063 | B67: 7 | C67: BYD | D67: App Store | E67: 2026 Q1 | F67: Notifications not working | G67: 0 | H67: 0 | I67: 0 | J67: 0 | K67: 0 | L67: 1 | M67: 0 | N67: 0 | O67: 0 | P67: 0 | Q67: 0 | R67: 1 | S67: 0 | T67: 0 | U67: 0
A68: B-AP-064 | B68: 8 | C68: BYD | D68: App Store | E68: 2025 Q4 | F68: Missing alarms, worse than Hyundai | G68: 0 | H68: 1 | I68: 0 | J68: 0 | K68: 0 | L68: 0 | M68: 0 | N68: 0 | O68: 0 | P68: 0 | Q68: 0 | R68: 0 | S68: 0 | T68: 0 | U68: 0
A69: B-AP-065 | B69: 9 | C69: BYD | D69: App Store | E69: 2025 Q4 | F69: Poor UX logic, slow interaction | G69: 0 | H69: 0 | I69: 1 | J69: 0 | K69: 0 | L69: 0 | M69: 0 | N69: 0 | O69: 0 | P69: 0 | Q69: 0 | R69: 0 | S69: 0 | T69: 0 | U69: 0
A70: B-AP-066 | B70: 10 | C70: BYD | D70: App Store | E70: 2025 Q4 | F70: Works but seat heating unreliable | G70: 0 | H70: 0 | I70: 0 | J70: 0 | K70: 0 | L70: 1 | M70: 0 | N70: 0 | O70: 0 | P70: 0 | Q70: 0 | R70: 0 | S70: 0 | T70: 0 | U70: 0
A71: B-AP-067 | B71: 11 | C71: BYD | D71: App Store | E71: 2025 Q3 | F71: Basic functions, no dark mode/widgets issues | G71: 0 | H71: 0 | I71: 0 | J71: 1 | K71: 0 | L71: 0 | M71: 0 | N71: 0 | O71: 0 | P71: 0 | Q71: 0 | R71: 1 | S71: 1 | T71: 0 | U71: 0
A72: B-AP-068 | B72: 12 | C72: BYD | D72: App Store | E72: 2025 Q2 | F72: Charging stop not working | G72: 0 | H72: 0 | I72: 0 | J72: 0 | K72: 0 | L72: 1 | M72: 0 | N72: 0 | O72: 0 | P72: 0 | Q72: 0 | R72: 0 | S72: 0 | T72: 0 | U72: 0
... A156: B-GO-152 | B156: 100391 | C156: BYD | D156: GoingElectric | E156: 2026 Q1 | F156: OTA update breaks infotainment, central display restarts, updates do not fix issue, settings and navigation unusable | G156: 0 | H156: 1 | I156: 0 | J156: 0 | K156: 0 | L156: 1 | M156: 0 | N156: 0 | O156: 0 | P156: 0 | Q156: 0 | R156: 1 | S156: 0 | T156: 0 | U156: 0

Sheet coding frequency
A1: Tesla | G1: BYD
A2: Category | B2: Pos | C2: Neg | D2: Total | G2: Category | H2: Pos | I2: Neg | J2: Total
A3: USE | B3: =SUM(Table911[USE+]) -> 17 | C3: =SUM(Table911[USE−]) -> 9 | D3: =SUM(B3:C3) -> 26 | G3: USE | H3: =SUM(Table11[USE+]) -> 42 | I3: =SUM(Table11[USE−]) -> 38 | J3: =SUM(H3:I3) -> 80
A4: UX | B4: =SUM(Table911[UX+]) -> 1 | C4: =SUM(Table911[UX−]) -> 9 | D4: =SUM(B4:C4) -> 10 | G4: UX | H4: =SUM(Table11[UX+]) -> 2 | I4: =SUM(Table11[UX−]) -> 11 | J4: =SUM(H4:I4) -> 13
A5: REL | B5: =SUM(Table911[REL+]) -> 3 | C5: =SUM(Table911[REL−]) -> 40 | D5: =SUM(B5:C5) -> 43 | G5: REL | H5: =SUM(Table11[REL+]) -> 0 | I5: =SUM(Table11[REL−]) -> 40 | J5: =SUM(H5:I5) -> 40
A6: TRUST | B6: =SUM(Table911[TRUST+]) -> 1 | C6: =SUM(Table911[TRUST−]) -> 10 | D6: =SUM(B6:C6) -> 11 | G6: TRUST | H6: =SUM(Table11[TRUST+]) -> 0 | I6: =SUM(Table11[TRUST−]) -> 5 | J6: =SUM(H6:I6) -> 5
A7: LOC | B7: =SUM(Table911[LOC+]) -> 0 | C7: =SUM(Table911[LOC−]) -> 28 | D7: =SUM(B7:C7) -> 28 | G7: LOC | H7: =SUM(Table11[LOC+]) -> 1 | I7: =SUM(Table11[LOC−]) -> 10 | J7: =SUM(H7:I7) -> 11
A8: DIGI | B8: =SUM(Table911[DIGI+]) -> 11 | C8: =SUM(Table911[DIGI−]) -> 27 | D8: =SUM(B8:C8) -> 38 | G8: DIGI | H8: =SUM(Table11[DIGI+]) -> 7 | I8: =SUM(Table11[DIGI−]) -> 38 | J8: =SUM(H8:I8) -> 45
A9: ISSUE | B9: =SUM(Table911[ISSUE]) -> 8 | D9: =SUM(B9:C9) -> 8 | G9: ISSUE | H9: =SUM(Table11[ISSUE]) -> 41 | J9: =SUM(H9:I9) -> 41
A10: AI | B10: =SUM(Table911[AI+]) -> 0 | C10: =SUM(Table911[AI−]) -> 0 | D10: =SUM(B10:C10) -> 0 | G10: AI | H10: =SUM(Table11[AI+]) -> 0 | I10: =SUM(Table911[AI−]) -> 0 | J10: =SUM(H10:I10) -> 0
